sparkvis/__init__.py
sparkvis-0.4.1.dist-info/LICENSE
sparkvis-0.4.1.dist-info/WHEEL
sparkvis-0.4.1.dist-info/METADATA
sparkvis-0.4.1.dist-info/RECORD
