Metadata-Version: 2.1
Name: sparkvis
Version: 0.4.1
Summary: Visualize tensors using Sparklines
License: MIT
Author: Shawn Presser
Author-email: shawnpresser@gmail.com
Requires-Python: >=3.6,<4.0
Classifier: License :: OSI Approved :: MIT License
Classifier: Programming Language :: Python :: 3
Classifier: Programming Language :: Python :: 3.6
Classifier: Programming Language :: Python :: 3.7
Classifier: Programming Language :: Python :: 3.8
Classifier: Programming Language :: Python :: 3.9
Requires-Dist: sparklines (>=0.4.2,<0.5.0)
